openph/__init__.py
openph/from_HBJSON/__init__.py
openph/from_HBJSON/create_phpp.py
openph/model/__init__.py
openph/model/areas.py
openph/model/climate.py
openph/model/components.py
openph/model/constants.py
openph/model/constructions.py
openph/model/enums.py
openph/model/envelope.py
openph/model/hvac/__init__.py
openph/model/hvac/hot_water.py
openph/model/hvac/hvac.py
openph/model/hvac/ventilation_device.py
openph/model/hvac/ventilation_system.py
openph/model/ihg.py
openph/model/loads/__init__.py
openph/model/loads/infiltration.py
openph/model/loads/ventilation.py
openph/model/programs/__init__.py
openph/model/programs/ventilation.py
openph/model/rooms.py
openph/model/schedules/__init__.py
openph/model/schedules/collection.py
openph/model/schedules/occupancy.py
openph/model/schedules/ventilation.py
openph/model/set_points.py
openph/phpp.py
openph/table_views/__init__.py
openph/table_views/areas.py
openph/table_views/climate.py
openph/table_views/cooling_demand.py
openph/table_views/ground.py
openph/table_views/heating_demand.py
openph/table_views/rooms.py
openph/table_views/ventilation.py
openph-0.1.1.dist-info/WHEEL
openph-0.1.1.dist-info/METADATA
openph-0.1.1.dist-info/RECORD
