Metadata-Version: 2.3
Name: openph
Version: 0.1.1
Summary: OpenPH - Open-source Passive House energy modeling and calculation engine
Author: PH-Tools
Author-email: PH-Tools <none@none.com>
License: GNU GENERAL PUBLIC LICENSE
Requires-Dist: phx
Requires-Dist: ph-units
Requires-Dist: honeybee-ph
Requires-Dist: pytest>=8.4.2 ; extra == 'dev'
Requires-Dist: openpyxl>=3.1.5 ; extra == 'dev'
Requires-Dist: rich>=14.2.0 ; extra == 'dev'
Requires-Python: >=3.10
Provides-Extra: dev
